{
	"system" : {
		"platform" : "windows64",
		"os_name" : "Windows 10",
		"os_version" : "10.0"
	},
	"error" : {
		"executable" : "quartus",
		"comment" : "not_applicable",
		"error_message" : "Access Violation at 0X000000005FEAD4B6",
		"source_file" : "unknown",
		"line" : "0",
		"stack_trace" : "\t 0x5fead4b5: QtGui4 + 0x5d4b5 (??1QWidget@@UEAA@XZ + 0x4a5)\n\t 0x5feadab5: QtGui4 + 0x5dab5 (??1QWidgetPrivate@@UEAA@XZ + 0x1c5)\n\t 0x60cbf752: QtCore4 + 0x11f752 (?deleteChildren@QObjectPrivate@@QEAAXXZ + 0xa2)\n\t 0x5fead7b7: QtGui4 + 0x5d7b7 (??1QWidget@@UEAA@XZ + 0x7a7)\n\t0x7ffc9f96e11b: SYS_QUI + 0x3e11b (??_EQUI_MDI_SUB_WND@@UEAAPEAXI@Z + 0x6b)\n\t 0x60cc0c94: QtCore4 + 0x120c94 (?event@QObject@@UEAA_NPEAVQEvent@@@Z + 0xa4)\n\t 0x5feb27f2: QtGui4 + 0x627f2 (?event@QWidget@@MEAA_NPEAVQEvent@@@Z + 0xd42)\n\t 0x5fe72c55: QtGui4 + 0x22c55 (?notify_helper@QApplicationPrivate@@QEAA_NPEAVQObject@@PEAVQEvent@@@Z + 0xf5)\n\t 0x5fe728ef: QtGui4 + 0x228ef (?notify@QApplication@@UEAA_NPEAVQObject@@PEAVQEvent@@@Z + 0x17bf)\n\t 0x60caec4b: QtCore4 + 0x10ec4b (?notifyInternal@QCoreApplication@@AEAA_NPEAVQObject@@PEAVQEvent@@@Z + 0x7b)\n\t 0x60cb0822: QtCore4 + 0x110822 (?sendPostedEvents@QCoreApplicationPrivate@@SAXPEAVQObject@@HPEAVQThreadData@@@Z + 0x2b2)\n\t 0x60bc8868: QtCore4 + 0x28868 (?q_func@QObjectPrivate@@AEAAPEAVQObject@@XZ + 0x198)\n\t 0x60bc9b60: QtCore4 + 0x29b60 (?terminate@QThread@@QEAAXXZ + 0xa0)\n\t0x7ffc1fbb8e90: sld_redq + 0x8e90 (??1REDQ_NODE_WIDGET@@UEAA@XZ + 0xb0)\n\t0x7ffc1fbb9ec3: sld_redq + 0x9ec3 (??_EREDQ_NODE_WIDGET@@UEAAPEAXI@Z + 0x13)\n\t0x7ffc1fbb8d4e: sld_redq + 0x8d4e (??1REDQ_DEVICE_WIDGET@@UEAA@XZ + 0xbe)\n\t0x7ffc1fbb9bf3: sld_redq + 0x9bf3 (??_EREDQ_DEVICE_WIDGET@@UEAAPEAXI@Z + 0x13)\n\t0x7ffc1fbb907e: sld_redq + 0x907e (??1REDQ_WIDGET@@UEAA@XZ + 0x3e)\n\t0x7ffc1fbba0d3: sld_redq + 0xa0d3 (??_EREDQ_WIDGET@@UEAAPEAXI@Z + 0x13)\n\t 0x60cbf752: QtCore4 + 0x11f752 (?deleteChildren@QObjectPrivate@@QEAAXXZ + 0xa2)\n\t 0x5fead7b7: QtGui4 + 0x5d7b7 (??1QWidget@@UEAA@XZ + 0x7a7)\n\t0x7ffc1fbb99f4: sld_redq + 0x99f4 (??_EQSplitter@@UEAAPEAXI@Z + 0x14)\n\t 0x60cbf752: QtCore4 + 0x11f752 (?deleteChildren@QObjectPrivate@@QEAAXXZ + 0xa2)\n\t 0x5fead7b7: QtGui4 + 0x5d7b7 (??1QWidget@@UEAA@XZ + 0x7a7)\n\t0x7ffc1fbb9e87: sld_redq + 0x9e87 (??_EREDQ_LAYOUT_WIDGET@@UEAAPEAXI@Z + 0x37)\n\t 0x60cbf752: QtCore4 + 0x11f752 (?deleteChildren@QObjectPrivate@@QEAAXXZ + 0xa2)\n\t 0x5fead7b7: QtGui4 + 0x5d7b7 (??1QWidget@@UEAA@XZ + 0x7a7)\n\t0x7ffc9f952cd4: SYS_QUI + 0x22cd4 (??1QUI_FRAME_WND@@UEAA@XZ + 0x454)\n\t0x7ffc1fbb9c47: sld_redq + 0x9c47 (??_EREDQ_FRAME_WND@@UEAAPEAXI@Z + 0x37)\n\t 0x60cc0c94: QtCore4 + 0x120c94 (?event@QObject@@UEAA_NPEAVQEvent@@@Z + 0xa4)\n\t 0x5feb27f2: QtGui4 + 0x627f2 (?event@QWidget@@MEAA_NPEAVQEvent@@@Z + 0xd42)\n\t 0x601ee830: QtGui4 + 0x39e830 (?event@QMainWindow@@MEAA_NPEAVQEvent@@@Z + 0x280)\n\t 0x5fe72c55: QtGui4 + 0x22c55 (?notify_helper@QApplicationPrivate@@QEAA_NPEAVQObject@@PEAVQEvent@@@Z + 0xf5)\n\t 0x5fe728ef: QtGui4 + 0x228ef (?notify@QApplication@@UEAA_NPEAVQObject@@PEAVQEvent@@@Z + 0x17bf)\n\t 0x60caec4b: QtCore4 + 0x10ec4b (?notifyInternal@QCoreApplication@@AEAA_NPEAVQObject@@PEAVQEvent@@@Z + 0x7b)\n\t 0x60cb0822: QtCore4 + 0x110822 (?sendPostedEvents@QCoreApplicationPrivate@@SAXPEAVQObject@@HPEAVQThreadData@@@Z + 0x2b2)\n\t 0x60cd4138: QtCore4 + 0x134138 (?processEvents@QEventDispatcherWin32@@UEAA_NV?$QFlags@W4ProcessEventsFlag@QEventLoop@@@@@Z + 0xb98)\n\t0x7ffcb7308230: USER32 + 0x18230 (DispatchMessageW + 0x740)\n\t0x7ffcb7307cf0: USER32 + 0x17cf0 (DispatchMessageW + 0x200)\n\t 0x60cd3982: QtCore4 + 0x133982 (?processEvents@QEventDispatcherWin32@@UEAA_NV?$QFlags@W4ProcessEventsFlag@QEventLoop@@@@@Z + 0x3e2)\n\t 0x5fed2004: QtGui4 + 0x82004 (?openPopup@QApplicationPrivate@@QEAAXPEAVQWidget@@@Z + 0x204)\n\t 0x60cabb7b: QtCore4 + 0x10bb7b (?exec@QEventLoop@@QEAAHV?$QFlags@W4ProcessEventsFlag@QEventLoop@@@@@Z + 0x22b)\n\t 0x60cae18f: QtCore4 + 0x10e18f (?exec@QCoreApplication@@SAHXZ + 0xdf)\n\t0x7ff7856f198b: quartus + 0x198b (?qgq_main@@YAHHPEAPEBD@Z + 0x8b)\n\t0x7ffc85c63258: CCL_MSG + 0x13258 (?msg_main_thread@@YAPEAXPEAX@Z + 0x18)\n\t0x7ffc85c64a5e: CCL_MSG + 0x14a5e (?msg_thread_wrapper@@YAPEAXP6APEAXPEAX@Z0@Z + 0x6e)\n\t0x7ffc85d76af0: ccl_mem + 0x16af0 (?mem_thread_wrapper@@YAPEAXP6APEAXPEAX@Z0@Z + 0x70)\n\t0x7ffc85c62af1: CCL_MSG + 0x12af1 (?msg_exe_main@@YAHHPEAPEBDP6AHH0@Z@Z + 0xa1)\n\t0x7ff7856f2777: quartus + 0x2777 (WinMain + 0x127)\n\t0x7ff7856f1f40: quartus + 0x1f40 (__tmainCRTStartup + 0x148)\n\t0x7ffcb794269c: KERNEL32 + 0x1269c (BaseThreadInitThunk + 0x1c)\n\t0x7ffcb91ca9f7: ntdll + 0x5a9f7 (RtlUserThreadStart + 0x27)\n",
		"subsystem" : "unknown"
	},
	"quartus" : {
		"quartus_bits" : "64",
		"version" : "20.1.0",
		"build" : "711",
		"edition" : "Lite Edition"
	}
}